nox/__init__.py
nox/main.py
nox/commands/__init__.py
nox/commands/datetime_commands.py
nox/commands/db_commands.py
nox/commands/docker_commands.py
nox/commands/encrypt_commands.py
nox/commands/env_commands.py
nox/commands/hash_commands.py
nox/commands/init_command.py
nox/commands/jwt_commands.py
nox/commands/kafka_commands.py
nox/commands/net_commands.py
nox/commands/redis_commands.py
nox/commands/s3_commands.py
nox/commands/secret_commands.py
nox/commands/uuid_commands.py
nox/config/__init__.py
nox/domains/Initializer.py
nox/domains/__init__.py
nox/domains/datetime_manager.py
nox/domains/db_manager.py
nox/domains/docker_manager.py
nox/domains/encrypt.py
nox/domains/env_manager.py
nox/domains/hash_manager.py
nox/domains/jwt_manager.py
nox/domains/kafka_manager.py
nox/domains/net_manager.py
nox/domains/redis_manager.py
nox/domains/s3_manager.py
nox/domains/secret_manager.py
nox/domains/uuid_generator.py
nox/plugins/__init__.py
nox/utils/__init__.py
tests/__init__.py
tests/datetime_test.py
tests/db_test.py
tests/docker_test.py
tests/env_test.py
tests/hash_commands_test.py
tests/init_test.py
tests/jwt_commands_test.py
tests/net_commands_test.py
tests/s3_comnmands_test.py
tests/secret_commands_test.py
tests/uuid_commands_test.py
tests/uuid_test.py
nox_cli-0.1.1.dist-info/LICENSE
nox_cli-0.1.1.dist-info/METADATA
nox_cli-0.1.1.dist-info/WHEEL
nox_cli-0.1.1.dist-info/entry_points.txt
nox_cli-0.1.1.dist-info/top_level.txt
nox_cli-0.1.1.dist-info/RECORD
